litert_torch/__init__.py
litert_torch/_config.py
litert_torch/cli.py
litert_torch/conftest.py
litert_torch/model.py
litert_torch/version.py
litert_torch/_convert/__init__.py
litert_torch/_convert/conversion.py
litert_torch/_convert/conversion_utils.py
litert_torch/_convert/converter.py
litert_torch/_convert/signature.py
litert_torch/_convert/to_channel_last_io.py
litert_torch/_convert/fx_passes/__init__.py
litert_torch/_convert/fx_passes/build_aten_composite_pass.py
litert_torch/_convert/fx_passes/cast_inputs_bf16_to_f32_pass.py
litert_torch/_convert/fx_passes/eliminate_dead_code_pass.py
litert_torch/_convert/fx_passes/inject_mlir_debuginfo_pass.py
litert_torch/_convert/fx_passes/remove_non_user_outputs_pass.py
litert_torch/_convert/fx_passes/optimize_layout_transposes_pass/__init__.py
litert_torch/_convert/fx_passes/optimize_layout_transposes_pass/_decomp_registry.py
litert_torch/_convert/fx_passes/optimize_layout_transposes_pass/layout_check.py
litert_torch/_convert/fx_passes/optimize_layout_transposes_pass/layout_mark.py
litert_torch/_convert/fx_passes/optimize_layout_transposes_pass/layout_rewrite.py
litert_torch/_convert/fx_passes/optimize_layout_transposes_pass/op_func_registry.py
litert_torch/_convert/fx_passes/optimize_layout_transposes_pass/pass_body.py
litert_torch/_convert/fx_passes/optimize_layout_transposes_pass/utils.py
litert_torch/_convert/fx_passes/optimize_layout_transposes_pass/layout_partitioners/__init__.py
litert_torch/_convert/fx_passes/optimize_layout_transposes_pass/layout_partitioners/greedy.py
litert_torch/_convert/fx_passes/optimize_layout_transposes_pass/layout_partitioners/min_cut.py
litert_torch/_convert/test/__init__.py
litert_torch/_convert/test/test_convert.py
litert_torch/_convert/test/test_convert_composites.py
litert_torch/_convert/test/test_convert_multisig.py
litert_torch/_convert/test/test_to_channel_last_io.py
litert_torch/debug/__init__.py
litert_torch/debug/culprit.py
litert_torch/debug/utils.py
litert_torch_nightly-0.9.0.dev20260201.dist-info/licenses/LICENSE
litert_torch_nightly-0.9.0.dev20260201.dist-info/METADATA
litert_torch_nightly-0.9.0.dev20260201.dist-info/WHEEL
litert_torch_nightly-0.9.0.dev20260201.dist-info/entry_points.txt
litert_torch_nightly-0.9.0.dev20260201.dist-info/top_level.txt
litert_torch_nightly-0.9.0.dev20260201.dist-info/RECORD
